spacy_language_detection/__init__.py
spacy_language_detection/spacy_language_detector.py
spacy_language_detection/version.py
tests/__init__.py
tests/requirements_spacy.py
tests/test_spacy_language_detector.py
spacy_language_detection-0.2.1.dist-info/LICENSE
spacy_language_detection-0.2.1.dist-info/METADATA
spacy_language_detection-0.2.1.dist-info/WHEEL
spacy_language_detection-0.2.1.dist-info/top_level.txt
spacy_language_detection-0.2.1.dist-info/RECORD
