Metadata-Version: 2.1
Name: spacy-language-detection
Version: 0.2.1
Summary: Fully customizable language detection for spaCy pipeline
Home-page: https://github.com/davebulaval/spacy-language-detection
Author: David Beauchemin
Author-email: david.beauchemin.5@ulaval.ca
License: LGPLv3
Download-URL: https://github.com/davebulaval/spacy-language-detection/archive/v0.2.1.zip
Platform: UNKNOWN
Classifier: Development Status :: 3 - Alpha
Classifier: Intended Audience :: Developers
Classifier: Intended Audience :: Education
Classifier: Intended Audience :: Science/Research
Classifier: License :: OSI Approved :: GNU Lesser General Public License v3 (LGPLv3)
Classifier: Programming Language :: Python :: 3
Classifier: Programming Language :: Python :: 3.7
Classifier: Programming Language :: Python :: 3.8
Classifier: Topic :: Software Development :: Libraries
Classifier: Topic :: Software Development :: Libraries :: Python Modules
Requires-Python: >=3.7
